DepthML/__init__.py
DepthML/block.py
DepthML/typing.py
DepthML/activations/__init__.py
DepthML/activations/base_activation.py
DepthML/activations/common_activations.py
DepthML/initializers/__init__.py
DepthML/initializers/base_initializer.py
DepthML/initializers/glorot.py
DepthML/initializers/kaiming.py
DepthML/initializers/zeros.py
DepthML/layers/__init__.py
DepthML/layers/base_layer.py
DepthML/layers/conv2d.py
DepthML/layers/flatten.py
DepthML/layers/input.py
DepthML/layers/linear.py
DepthML/losses/__init__.py
DepthML/losses/base_loss.py
DepthML/losses/categorical_cross_entropy.py
DepthML/losses/mean_squared_error.py
DepthML/losses/softmax_categorical_cross_entropy.py
DepthML/models/__init__.py
DepthML/models/base_model.py
DepthML/models/sequential.py
DepthML/optimizers/__init__.py
DepthML/optimizers/base_optimizer.py
DepthML/optimizers/sgd.py
DepthML/utils/__init__.py
DepthML/utils/clip_grad_norm.py
DepthML/utils/get_xp.py
depthml-0.2.0.dist-info/licenses/LICENSE
depthml-0.2.0.dist-info/METADATA
depthml-0.2.0.dist-info/WHEEL
depthml-0.2.0.dist-info/top_level.txt
depthml-0.2.0.dist-info/RECORD
