Metadata-Version: 2.4
Name: DepthML
Version: 0.2.0
License-File: LICENSE
Requires-Dist: numpy>=2.3.1
Requires-Dist: depthtensor>=2.0.2
Dynamic: license-file
